kubepot/__init__.py
kubepot-0.0.1.dist-info/METADATA
kubepot-0.0.1.dist-info/WHEEL
kubepot-0.0.1.dist-info/top_level.txt
kubepot-0.0.1.dist-info/RECORD
