Metadata-Version: 2.1
Name: kubepot
Version: 0.0.1
Summary: Jaqpot Kubernetes Client.
Home-page: https://github.com/euclia/kubepot
Author: Pantelis Karatzas
Author-email: pantelispanka@gmail.com
License: MIT License
Requires-Dist: kubernetes
